Metadata-Version: 2.1
Name: segment-anything-py
Version: 1.0.1
Summary: An unofficial Python package for Meta AI's Segment Anything Model
Home-page: https://github.com/opengeos/segment-anything
Author: Qiusheng Wu
Author-email: giswqs@gmail.com
License: Apache Software License 2.0
Classifier: Intended Audience :: Developers
Classifier: License :: OSI Approved :: Apache Software License
Classifier: Natural Language :: English
Classifier: Programming Language :: Python :: 3.8
Classifier: Programming Language :: Python :: 3.9
Classifier: Programming Language :: Python :: 3.10
Classifier: Programming Language :: Python :: 3.11
Requires-Python: >=3.8
License-File: LICENSE
Requires-Dist: torch >=1.7
Requires-Dist: torchvision >=0.8
Provides-Extra: all
Requires-Dist: matplotlib ; extra == 'all'
Requires-Dist: pycocotools ; extra == 'all'
Requires-Dist: opencv-python ; extra == 'all'
Requires-Dist: onnx ; extra == 'all'
Requires-Dist: onnxruntime ; extra == 'all'
Provides-Extra: dev
Requires-Dist: flake8 ; extra == 'dev'
Requires-Dist: isort ; extra == 'dev'
Requires-Dist: black ; extra == 'dev'
Requires-Dist: mypy ; extra == 'dev'
